facetracker/__init__.py
facetracker/_version.py
facetracker/tracker.py
facetracker-0.2.dist-info/licenses/LICENSE
facetracker-0.2.dist-info/METADATA
facetracker-0.2.dist-info/WHEEL
facetracker-0.2.dist-info/entry_points.txt
facetracker-0.2.dist-info/top_level.txt
facetracker-0.2.dist-info/RECORD
